{
    "id": 147,
    "min": [
        34327.980021,
        -8591.384295,
        9365.0
    ],
    "max": [
        37633.980021,
        -385.384295,
        12590.0
    ],
    "objects": {
        "CV_GKW": [],
        "ET": [
            {
                "name": "3G2,5:2347",
                "min": [
                    37457.123966,
                    -4051.378717,
                    12226.0
                ],
                "max": [
                    37468.523966,
                    -4039.978717,
                    12231.7
                ]
            },
            {
                "name": "3G2,5:2348",
                "min": [
                    37411.823966,
                    -4051.347492,
                    12231.7
                ],
                "max": [
                    37468.523966,
                    -4040.009943,
                    12288.4
                ]
            },
            {
                "name": "CHP60-BW:0372",
                "min": [
                    35610.994954,
                    -6018.409295,
                    12275.0
                ],
                "max": [
                    35770.994954,
                    -5858.409295,
                    12353.0
                ]
            },
            {
                "name": "CHP60-BW:0375",
                "min": [
                    35373.51689,
                    -1921.759329,
                    12275.0
                ],
                "max": [
                    35533.51689,
                    -1761.759329,
                    12353.0
                ]
            },
            {
                "name": "asp 1 fase:108",
                "min": [
                    36204.405715,
                    -7706.902244,
                    12037.5
                ],
                "max": [
                    36279.405715,
                    -7704.902244,
                    12112.5
                ]
            },
            {
                "name": "lasdoos AK2 wand:45",
                "min": [
                    37445.979998,
                    -3975.678567,
                    12085.0
                ],
                "max": [
                    37490.979998,
                    -3855.678567,
                    12175.0
                ]
            },
            {
                "name": "ledige leiding:0044",
                "min": [
                    34442.673894,
                    -3166.534295,
                    11234.65
                ],
                "max": [
                    34523.373894,
                    -3150.534295,
                    11315.35
                ]
            },
            {
                "name": "schakelaar enkelpolig:0135",
                "min": [
                    35833.659887,
                    -4269.657578,
                    10684.65
                ],
                "max": [
                    35914.359887,
                    -4250.834295,
                    10765.35
                ]
            },
            {
                "name": "schakelaar wissel:0023",
                "min": [
                    34878.423894,
                    -735.662257,
                    10684.65
                ],
                "max": [
                    34897.247177,
                    -654.962257,
                    10765.35
                ]
            },
            {
                "name": "standaard:33",
                "min": [
                    34470.480021,
                    -1223.384363,
                    11275.0
                ],
                "max": [
                    34559.480021,
                    -1003.384363,
                    11970.0
                ]
            },
            {
                "name": "wcd enkelvoudig:0227",
                "min": [
                    34465.880021,
                    -778.734363,
                    11969.65
                ],
                "max": [
                    34481.880021,
                    -698.034363,
                    12050.35
                ]
            },
            {
                "name": "wcd inbouw tweevoudig:0382",
                "min": [
                    37479.609887,
                    -7297.284295,
                    9934.65
                ],
                "max": [
                    37495.609887,
                    -7145.484295,
                    10015.35
                ]
            },
            {
                "name": "wcd inbouw tweevoudig:0383",
                "min": [
                    37479.609887,
                    -5251.334295,
                    9934.65
                ],
                "max": [
                    37495.609887,
                    -5099.534295,
                    10015.35
                ]
            },
            {
                "name": "wcd inbouw tweevoudig:0386",
                "min": [
                    34465.880021,
                    -998.734363,
                    11274.1
                ],
                "max": [
                    34481.880021,
                    -918.034363,
                    11425.9
                ]
            }
        ],
        "lucht": [],
        "Riolering": [],
        "Sanitair": []
    },
    "adjacent": [
        [
            245
        ],
        [
            151
        ],
        [],
        [
            148
        ],
        [
            231
        ],
        [
            185
        ]
    ]
}