{
    "id": 3,
    "min": [
        -174.0,
        16426.0,
        -310.0
    ],
    "max": [
        9032.0,
        19732.0,
        2915.0
    ],
    "objects": {
        "CV_GKW": [],
        "ET": [
            {
                "name": "CHP60-BW:0020",
                "min": [
                    2869.0,
                    18089.0,
                    2600.0
                ],
                "max": [
                    3029.0,
                    18249.0,
                    2678.0
                ]
            },
            {
                "name": "CHP60-BW:0023",
                "min": [
                    6082.25,
                    16524.25,
                    2600.0
                ],
                "max": [
                    6242.25,
                    16684.25,
                    2678.0
                ]
            },
            {
                "name": "CHP60-BW:0133",
                "min": [
                    2216.0,
                    18099.073,
                    2600.0
                ],
                "max": [
                    2376.0,
                    18259.073,
                    2678.0
                ]
            },
            {
                "name": "CHP60-BW:0134",
                "min": [
                    5482.25,
                    16524.25,
                    2600.0
                ],
                "max": [
                    5642.25,
                    16684.25,
                    2678.0
                ]
            },
            {
                "name": "WCD enkelvoudig waterdicht:112",
                "min": [
                    5346.75,
                    19556.1,
                    1236.5
                ],
                "max": [
                    5351.25,
                    19569.1,
                    1239.994916
                ]
            },
            {
                "name": "WCD enkelvoudig waterdicht:113",
                "min": [
                    5346.75,
                    19556.1,
                    1200.005084
                ],
                "max": [
                    5351.25,
                    19569.1,
                    1203.5
                ]
            },
            {
                "name": "WCD enkelvoudig waterdicht:114",
                "min": [
                    5329.189965,
                    19557.1,
                    1222.75
                ],
                "max": [
                    5332.5,
                    19569.1,
                    1231.302655
                ]
            },
            {
                "name": "WCD enkelvoudig waterdicht:115",
                "min": [
                    5329.189965,
                    19557.1,
                    1208.697345
                ],
                "max": [
                    5332.5,
                    19569.1,
                    1217.25
                ]
            },
            {
                "name": "WCD enkelvoudig waterdicht:116",
                "min": [
                    5365.5,
                    19557.1,
                    1222.75
                ],
                "max": [
                    5368.810035,
                    19569.1,
                    1231.302655
                ]
            },
            {
                "name": "WCD enkelvoudig waterdicht:117",
                "min": [
                    5365.5,
                    19557.1,
                    1208.697345
                ],
                "max": [
                    5368.810035,
                    19569.1,
                    1217.25
                ]
            },
            {
                "name": "WCD enkelvoudig waterdicht:118",
                "min": [
                    5328.0,
                    19563.5,
                    1199.023786
                ],
                "max": [
                    5370.0,
                    19570.1,
                    1240.976214
                ]
            },
            {
                "name": "WCD enkelvoudig waterdicht:119",
                "min": [
                    5322.0,
                    19554.1,
                    1193.0
                ],
                "max": [
                    5376.0,
                    19563.5,
                    1247.0
                ]
            },
            {
                "name": "WCD enkelvoudig waterdicht:120",
                "min": [
                    5308.65,
                    19555.1,
                    1179.65
                ],
                "max": [
                    5389.35,
                    19558.9,
                    1260.35
                ]
            },
            {
                "name": "WCD enkelvoudig waterdicht:121",
                "min": [
                    5308.65,
                    19558.9,
                    1179.65
                ],
                "max": [
                    5389.35,
                    19565.5,
                    1260.35
                ]
            },
            {
                "name": "asp 1 fase:24",
                "min": [
                    7294.5,
                    17389.0,
                    132.5
                ],
                "max": [
                    7369.5,
                    17391.0,
                    207.5
                ]
            },
            {
                "name": "asp 1 fase:25",
                "min": [
                    682.5,
                    16624.176059,
                    2420.5
                ],
                "max": [
                    684.5,
                    16699.176059,
                    2495.5
                ]
            },
            {
                "name": "brandmelder:0010",
                "min": [
                    2197.4,
                    18080.473,
                    2543.5
                ],
                "max": [
                    2394.6,
                    18277.673,
                    2600.0
                ]
            },
            {
                "name": "brandmelder:0011",
                "min": [
                    5463.65,
                    16505.65,
                    2543.5
                ],
                "max": [
                    5660.85,
                    16702.85,
                    2600.0
                ]
            },
            {
                "name": "ledige leiding:0015",
                "min": [
                    1753.65,
                    16469.85,
                    259.65
                ],
                "max": [
                    1834.35,
                    16485.85,
                    340.35
                ]
            },
            {
                "name": "ledige leiding:0016",
                "min": [
                    5411.65,
                    17384.4,
                    1479.65
                ],
                "max": [
                    5492.35,
                    17400.4,
                    1560.35
                ]
            },
            {
                "name": "ledige leiding:0061",
                "min": [
                    2380.65,
                    16600.65,
                    259.65
                ],
                "max": [
                    2461.35,
                    16616.65,
                    340.35
                ]
            },
            {
                "name": "ledige leiding:0062",
                "min": [
                    2130.65,
                    16600.65,
                    259.65
                ],
                "max": [
                    2211.35,
                    16616.65,
                    340.35
                ]
            },
            {
                "name": "ledige leiding:0104",
                "min": [
                    2003.65,
                    16469.85,
                    259.65
                ],
                "max": [
                    2084.35,
                    16485.85,
                    340.35
                ]
            },
            {
                "name": "schakelaar enkelpolig tek:0004",
                "min": [
                    5528.65,
                    17385.4,
                    2179.65
                ],
                "max": [
                    5609.35,
                    17404.223283,
                    2260.35
                ]
            },
            {
                "name": "schakelaar wissel:0007",
                "min": [
                    3391.65,
                    16600.65,
                    1009.65
                ],
                "max": [
                    3472.35,
                    16619.473283,
                    1090.35
                ]
            },
            {
                "name": "schakelaar wissel:0042",
                "min": [
                    3355.65,
                    19563.776717,
                    1009.65
                ],
                "max": [
                    3436.35,
                    19582.6,
                    1090.35
                ]
            },
            {
                "name": "standaard:6",
                "min": [
                    7359.0,
                    16758.0,
                    1635.0
                ],
                "max": [
                    7579.0,
                    16847.0,
                    2260.0
                ]
            },
            {
                "name": "wcd enkelvoudig op aparte groep:0036",
                "min": [
                    6133.15,
                    17294.6,
                    1009.65
                ],
                "max": [
                    6213.85,
                    17310.6,
                    1090.35
                ]
            },
            {
                "name": "wcd enkelvoudig op aparte groep:0037",
                "min": [
                    6238.85,
                    17294.6,
                    1009.65
                ],
                "max": [
                    6319.55,
                    17310.6,
                    1090.35
                ]
            },
            {
                "name": "wcd inbouw tweevoudig:0015",
                "min": [
                    1458.1,
                    16469.85,
                    259.65
                ],
                "max": [
                    1609.9,
                    16485.85,
                    340.35
                ]
            },
            {
                "name": "wcd inbouw tweevoudig:0086",
                "min": [
                    3320.1,
                    19566.6,
                    259.65
                ],
                "max": [
                    3471.9,
                    19582.6,
                    340.35
                ]
            },
            {
                "name": "wcd inbouw tweevoudig:0103",
                "min": [
                    2595.1,
                    16600.65,
                    259.65
                ],
                "max": [
                    2746.9,
                    16616.65,
                    340.35
                ]
            },
            {
                "name": "wcd inbouw tweevoudig:0152",
                "min": [
                    1120.1,
                    19566.6,
                    259.65
                ],
                "max": [
                    1271.9,
                    19582.6,
                    340.35
                ]
            },
            {
                "name": "wcd opbouw enkelvoudig:0006",
                "min": [
                    7193.5,
                    16816.6,
                    2510.75
                ],
                "max": [
                    7274.5,
                    16851.6,
                    2589.25
                ]
            }
        ],
        "lucht": [],
        "Riolering": [],
        "Sanitair": []
    },
    "adjacent": [
        [
            4
        ],
        [],
        [
            2
        ],
        [],
        [
            23
        ],
        []
    ]
}