{
    "id": 46,
    "min": [
        19026.0,
        25326.0,
        2915.0
    ],
    "max": [
        28232.0,
        28632.0,
        6140.0
    ],
    "objects": {
        "CV_GKW": [],
        "ET": [
            {
                "name": "CHP60-BW:0057",
                "min": [
                    21354.0,
                    26895.562388,
                    5825.0
                ],
                "max": [
                    21514.0,
                    27055.562388,
                    5903.0
                ]
            },
            {
                "name": "CHP60-BW:0058",
                "min": [
                    25174.0,
                    26895.562388,
                    5825.0
                ],
                "max": [
                    25334.0,
                    27055.562388,
                    5903.0
                ]
            },
            {
                "name": "CHP60-BW:0173",
                "min": [
                    22829.0,
                    26894.053422,
                    5825.0
                ],
                "max": [
                    22989.0,
                    27054.053422,
                    5903.0
                ]
            },
            {
                "name": "Part1.sat:21",
                "min": [
                    20870.459066,
                    25507.0,
                    4455.618286
                ],
                "max": [
                    20871.946016,
                    25508.0,
                    4458.676166
                ]
            },
            {
                "name": "Part2.sat:21",
                "min": [
                    20846.663923,
                    25506.0,
                    4446.854224
                ],
                "max": [
                    20848.569037,
                    25508.0,
                    4449.966444
                ]
            },
            {
                "name": "Part3.sat:21",
                "min": [
                    20838.500495,
                    25506.0,
                    4423.287523
                ],
                "max": [
                    20840.293727,
                    25507.0,
                    4426.51372
                ]
            },
            {
                "name": "asp 1 fase:48",
                "min": [
                    27358.214425,
                    28193.5,
                    5787.5
                ],
                "max": [
                    27360.214425,
                    28268.5,
                    5862.5
                ]
            },
            {
                "name": "asp 1 fase:101",
                "min": [
                    21376.5,
                    25496.0,
                    4987.5
                ],
                "max": [
                    21451.5,
                    25498.0,
                    5062.5
                ]
            },
            {
                "name": "brandmelder:0036",
                "min": [
                    22810.4,
                    26875.453422,
                    5768.5
                ],
                "max": [
                    23007.6,
                    27072.653422,
                    5825.0
                ]
            },
            {
                "name": "ledige leiding:0142",
                "min": [
                    21048.65,
                    28461.403422,
                    5584.65
                ],
                "max": [
                    21129.35,
                    28477.403422,
                    5665.35
                ]
            },
            {
                "name": "wcd enkelvoudig:0033",
                "min": [
                    22505.65,
                    25491.4,
                    5105.65
                ],
                "max": [
                    22586.35,
                    25507.4,
                    5186.35
                ]
            },
            {
                "name": "wcd enkelvoudig op aparte groep:0017",
                "min": [
                    21855.675316,
                    25491.4,
                    3284.65
                ],
                "max": [
                    21936.375316,
                    25507.4,
                    3365.35
                ]
            },
            {
                "name": "wcd inbouw tweevoudig:0035",
                "min": [
                    23970.1,
                    25491.4,
                    3484.65
                ],
                "max": [
                    24121.9,
                    25507.4,
                    3565.35
                ]
            },
            {
                "name": "wcd inbouw tweevoudig:0074",
                "min": [
                    21820.125316,
                    25491.4,
                    4384.65
                ],
                "max": [
                    21971.925316,
                    25507.4,
                    4465.35
                ]
            },
            {
                "name": "wcd inbouw tweevoudig:0139",
                "min": [
                    20585.1,
                    25491.4,
                    4384.65
                ],
                "max": [
                    20736.9,
                    25507.4,
                    4465.35
                ]
            },
            {
                "name": "wcd inbouw tweevoudig:0180",
                "min": [
                    26866.1,
                    25491.4,
                    3484.65
                ],
                "max": [
                    27017.9,
                    25507.4,
                    3565.35
                ]
            }
        ],
        "lucht": [],
        "Riolering": [],
        "Sanitair": []
    },
    "adjacent": [
        [
            35
        ],
        [],
        [
            34
        ],
        [],
        [],
        [
            40
        ]
    ]
}