{
    "id": 80,
    "min": [
        34327.936147,
        2908.615855,
        -310.0
    ],
    "max": [
        37633.936147,
        11114.615855,
        2915.0
    ],
    "objects": {
        "CV_GKW": [],
        "ET": [
            {
                "name": "3G2,5:151",
                "min": [
                    35752.007207,
                    8706.24363,
                    2602.0
                ],
                "max": [
                    37483.686147,
                    8717.64363,
                    2613.4
                ]
            },
            {
                "name": "3G2,5:152",
                "min": [
                    35695.307207,
                    8706.24363,
                    2551.0
                ],
                "max": [
                    35706.707207,
                    8717.64363,
                    2556.7
                ]
            },
            {
                "name": "3G2,5:153",
                "min": [
                    37528.986147,
                    8645.615855,
                    2602.0
                ],
                "max": [
                    37540.386147,
                    8660.94363,
                    2613.4
                ]
            },
            {
                "name": "3G2,5:154",
                "min": [
                    37528.986147,
                    8588.915855,
                    2451.0
                ],
                "max": [
                    37540.386147,
                    8600.315855,
                    2556.7
                ]
            },
            {
                "name": "3G2,5:155",
                "min": [
                    35695.307207,
                    8706.274856,
                    2556.7
                ],
                "max": [
                    35752.007207,
                    8717.612405,
                    2613.4
                ]
            },
            {
                "name": "3G2,5:156",
                "min": [
                    36322.891621,
                    5511.79677,
                    2602.0
                ],
                "max": [
                    37483.686147,
                    5523.19677,
                    2613.4
                ]
            },
            {
                "name": "3G2,5:157",
                "min": [
                    36266.191621,
                    5511.79677,
                    2551.0
                ],
                "max": [
                    36277.591621,
                    5523.19677,
                    2556.7
                ]
            },
            {
                "name": "3G2,5:158",
                "min": [
                    37528.986147,
                    5568.49677,
                    2602.0
                ],
                "max": [
                    37540.386147,
                    5970.615923,
                    2613.4
                ]
            },
            {
                "name": "3G2,5:159",
                "min": [
                    37528.986147,
                    6015.915923,
                    2451.0
                ],
                "max": [
                    37540.386147,
                    6027.315923,
                    2556.7
                ]
            },
            {
                "name": "3G2,5:160",
                "min": [
                    37529.017372,
                    5970.615923,
                    2556.7
                ],
                "max": [
                    37540.354922,
                    6027.315923,
                    2613.4
                ]
            },
            {
                "name": "3G2,5:161",
                "min": [
                    37483.686147,
                    5511.79677,
                    2602.031225
                ],
                "max": [
                    37540.386147,
                    5568.49677,
                    2613.368775
                ]
            },
            {
                "name": "3G2,5:162",
                "min": [
                    36266.191621,
                    5511.827995,
                    2556.7
                ],
                "max": [
                    36322.891621,
                    5523.165545,
                    2613.4
                ]
            },
            {
                "name": "3G2,5:163",
                "min": [
                    36246.191621,
                    5511.79677,
                    2351.0
                ],
                "max": [
                    36257.591621,
                    5523.19677,
                    2556.7
                ]
            },
            {
                "name": "3G2,5:164",
                "min": [
                    36246.191621,
                    5568.49677,
                    2602.0
                ],
                "max": [
                    36257.591621,
                    8640.94363,
                    2613.4
                ]
            },
            {
                "name": "3G2,5:165",
                "min": [
                    36246.222846,
                    5511.79677,
                    2556.7
                ],
                "max": [
                    36257.560396,
                    5568.49677,
                    2613.4
                ]
            },
            {
                "name": "3G2,5:166",
                "min": [
                    35752.007207,
                    8686.24363,
                    2602.0
                ],
                "max": [
                    36200.891621,
                    8697.64363,
                    2613.4
                ]
            },
            {
                "name": "3G2,5:167",
                "min": [
                    35695.307207,
                    8686.24363,
                    2551.0
                ],
                "max": [
                    35706.707207,
                    8697.64363,
                    2556.7
                ]
            },
            {
                "name": "3G2,5:168",
                "min": [
                    36200.891621,
                    8640.94363,
                    2602.031225
                ],
                "max": [
                    36257.591621,
                    8697.64363,
                    2613.368775
                ]
            },
            {
                "name": "3G2,5:169",
                "min": [
                    35695.307207,
                    8686.274856,
                    2556.7
                ],
                "max": [
                    35752.007207,
                    8697.612405,
                    2613.4
                ]
            },
            {
                "name": "3G2,5:170",
                "min": [
                    36322.891621,
                    5491.79677,
                    2602.0
                ],
                "max": [
                    37483.686147,
                    5503.19677,
                    2613.4
                ]
            },
            {
                "name": "3G2,5:171",
                "min": [
                    36266.191621,
                    5491.79677,
                    2551.0
                ],
                "max": [
                    36277.591621,
                    5503.19677,
                    2556.7
                ]
            },
            {
                "name": "3G2,5:172",
                "min": [
                    37528.986147,
                    3602.615923,
                    2602.0
                ],
                "max": [
                    37540.386147,
                    5446.49677,
                    2613.4
                ]
            },
            {
                "name": "3G2,5:173",
                "min": [
                    37528.986147,
                    3545.915923,
                    2451.0
                ],
                "max": [
                    37540.386147,
                    3557.315923,
                    2556.7
                ]
            },
            {
                "name": "3G2,5:174",
                "min": [
                    37529.017372,
                    3545.915923,
                    2556.7
                ],
                "max": [
                    37540.354922,
                    3602.615923,
                    2613.4
                ]
            },
            {
                "name": "3G2,5:175",
                "min": [
                    37483.686147,
                    5446.49677,
                    2602.031225
                ],
                "max": [
                    37540.386147,
                    5503.19677,
                    2613.368775
                ]
            },
            {
                "name": "3G2,5:176",
                "min": [
                    36266.191621,
                    5491.827995,
                    2556.7
                ],
                "max": [
                    36322.891621,
                    5503.165545,
                    2613.4
                ]
            },
            {
                "name": "3G2,5:2070",
                "min": [
                    37483.686147,
                    8660.94363,
                    2602.031225
                ],
                "max": [
                    37540.386147,
                    8717.64363,
                    2613.368775
                ]
            },
            {
                "name": "3G2,5:2071",
                "min": [
                    37529.017372,
                    8588.915855,
                    2556.7
                ],
                "max": [
                    37540.354922,
                    8645.615855,
                    2613.4
                ]
            },
            {
                "name": "3G2,5:2229",
                "min": [
                    35752.007207,
                    8726.24363,
                    2602.0
                ],
                "max": [
                    37445.131013,
                    8737.64363,
                    2613.4
                ]
            },
            {
                "name": "3G2,5:2230",
                "min": [
                    35695.307207,
                    8726.24363,
                    2551.0
                ],
                "max": [
                    35706.707207,
                    8737.64363,
                    2556.7
                ]
            },
            {
                "name": "3G2,5:2231",
                "min": [
                    35695.307207,
                    8726.274856,
                    2556.7
                ],
                "max": [
                    35752.007207,
                    8737.612405,
                    2613.4
                ]
            },
            {
                "name": "3G2,5:2232",
                "min": [
                    37490.431013,
                    8782.94363,
                    2602.0
                ],
                "max": [
                    37501.831013,
                    9951.75098,
                    2613.4
                ]
            },
            {
                "name": "3G2,5:2233",
                "min": [
                    37490.431013,
                    9997.05098,
                    2551.0
                ],
                "max": [
                    37501.831013,
                    10008.45098,
                    2556.7
                ]
            },
            {
                "name": "3G2,5:2234",
                "min": [
                    37445.131013,
                    8726.24363,
                    2602.031225
                ],
                "max": [
                    37501.831013,
                    8782.94363,
                    2613.368775
                ]
            },
            {
                "name": "3G2,5:2235",
                "min": [
                    37490.462238,
                    9951.75098,
                    2556.7
                ],
                "max": [
                    37501.799787,
                    10008.45098,
                    2613.4
                ]
            },
            {
                "name": "3G2,5:2236",
                "min": [
                    37470.431013,
                    8802.94363,
                    2602.0
                ],
                "max": [
                    37481.831013,
                    9951.75098,
                    2613.4
                ]
            },
            {
                "name": "3G2,5:2237",
                "min": [
                    37470.431013,
                    9997.05098,
                    2551.0
                ],
                "max": [
                    37481.831013,
                    10008.45098,
                    2556.7
                ]
            },
            {
                "name": "3G2,5:2238",
                "min": [
                    35752.007207,
                    8746.24363,
                    2602.0
                ],
                "max": [
                    37425.131013,
                    8757.64363,
                    2613.4
                ]
            },
            {
                "name": "3G2,5:2239",
                "min": [
                    35695.307207,
                    8746.24363,
                    2551.0
                ],
                "max": [
                    35706.707207,
                    8757.64363,
                    2556.7
                ]
            },
            {
                "name": "3G2,5:2240",
                "min": [
                    35695.307207,
                    8746.274856,
                    2556.7
                ],
                "max": [
                    35752.007207,
                    8757.612405,
                    2613.4
                ]
            },
            {
                "name": "3G2,5:2241",
                "min": [
                    37425.131013,
                    8746.24363,
                    2602.031225
                ],
                "max": [
                    37481.831013,
                    8802.94363,
                    2613.368775
                ]
            },
            {
                "name": "3G2,5:2242",
                "min": [
                    37470.462238,
                    9951.75098,
                    2556.7
                ],
                "max": [
                    37481.799787,
                    10008.45098,
                    2613.4
                ]
            },
            {
                "name": "CHP60-BW:0013",
                "min": [
                    36171.891621,
                    5427.49677,
                    2600.0
                ],
                "max": [
                    36331.891621,
                    5587.49677,
                    2678.0
                ]
            },
            {
                "name": "CHP60-BW:0014",
                "min": [
                    35611.007207,
                    8621.94363,
                    2600.0
                ],
                "max": [
                    35771.007207,
                    8781.94363,
                    2678.0
                ]
            },
            {
                "name": "CHP60-BW:0015",
                "min": [
                    34526.672328,
                    4432.986254,
                    2600.0
                ],
                "max": [
                    34686.672328,
                    4592.986254,
                    2678.0
                ]
            },
            {
                "name": "asp 1 fase:4",
                "min": [
                    34533.336147,
                    10236.115855,
                    2362.5
                ],
                "max": [
                    34608.336147,
                    10238.115855,
                    2437.5
                ]
            },
            {
                "name": "lasdoos AK2:2",
                "min": [
                    34514.3284,
                    3119.610448,
                    -45.0
                ],
                "max": [
                    34604.3284,
                    3239.610448,
                    -0.0
                ]
            },
            {
                "name": "wcd enkelvoudig:0008",
                "min": [
                    34485.586147,
                    3272.587255,
                    -40.35
                ],
                "max": [
                    34566.286147,
                    3288.587255,
                    40.35
                ]
            },
            {
                "name": "wcd inbouw tweevoudig:0016",
                "min": [
                    37479.766013,
                    8518.715855,
                    259.65
                ],
                "max": [
                    37495.766013,
                    8670.515855,
                    340.35
                ]
            },
            {
                "name": "wcd inbouw tweevoudig:0017",
                "min": [
                    37479.766013,
                    3475.715923,
                    259.65
                ],
                "max": [
                    37495.766013,
                    3627.515923,
                    340.35
                ]
            },
            {
                "name": "wcd inbouw tweevoudig:0018",
                "min": [
                    37479.766013,
                    5945.715923,
                    259.65
                ],
                "max": [
                    37495.766013,
                    6097.515923,
                    340.35
                ]
            },
            {
                "name": "wcd inbouw tweevoudig waterdicht:0033",
                "min": [
                    36826.036147,
                    10231.515855,
                    259.65
                ],
                "max": [
                    36977.836147,
                    10247.515855,
                    340.35
                ]
            }
        ],
        "lucht": [],
        "Riolering": [],
        "Sanitair": []
    },
    "adjacent": [
        [],
        [
            87
        ],
        [
            2
        ],
        [
            79
        ],
        [
            101
        ],
        []
    ]
}