{
    "id": 40,
    "min": [
        19026.0,
        25326.0,
        -310.0
    ],
    "max": [
        28232.0,
        28632.0,
        2915.0
    ],
    "objects": {
        "CV_GKW": [],
        "ET": [
            {
                "name": "3G2,5:771",
                "min": [
                    24122.9,
                    25419.74775,
                    294.3
                ],
                "max": [
                    26866.1,
                    25431.14775,
                    305.7
                ]
            },
            {
                "name": "3G2,5:772",
                "min": [
                    24041.3,
                    25419.74775,
                    340.35
                ],
                "max": [
                    24052.7,
                    25431.14775,
                    1140.35
                ]
            },
            {
                "name": "3G2,5:773",
                "min": [
                    20643.55,
                    25424.55,
                    1240.35
                ],
                "max": [
                    20654.95,
                    25435.95,
                    2329.629263
                ]
            },
            {
                "name": "3G2,5:774",
                "min": [
                    20717.05,
                    25424.55,
                    1240.35
                ],
                "max": [
                    20728.45,
                    25435.95,
                    1749.0
                ]
            },
            {
                "name": "3G2,5:775",
                "min": [
                    20773.75,
                    25424.55,
                    1794.3
                ],
                "max": [
                    21376.5,
                    25435.95,
                    1805.7
                ]
            },
            {
                "name": "3G2,5:776",
                "min": [
                    20717.05,
                    25424.581225,
                    1749.0
                ],
                "max": [
                    20773.75,
                    25435.918775,
                    1805.7
                ]
            },
            {
                "name": "3G2,5:777",
                "min": [
                    20761.9,
                    25424.55,
                    1194.3
                ],
                "max": [
                    21820.125316,
                    25435.95,
                    1205.7
                ]
            },
            {
                "name": "3G2,5:778",
                "min": [
                    21890.325316,
                    25424.55,
                    140.35
                ],
                "max": [
                    21901.725316,
                    25435.95,
                    1159.65
                ]
            },
            {
                "name": "3G2,5:779",
                "min": [
                    21971.925316,
                    25424.55,
                    1194.3
                ],
                "max": [
                    22495.0,
                    25435.95,
                    1205.7
                ]
            },
            {
                "name": "3G2,5:780",
                "min": [
                    22540.3,
                    25424.55,
                    1251.0
                ],
                "max": [
                    22551.7,
                    25435.95,
                    1880.65
                ]
            },
            {
                "name": "3G2,5:781",
                "min": [
                    22495.0,
                    25424.581225,
                    1194.3
                ],
                "max": [
                    22551.7,
                    25435.918775,
                    1251.0
                ]
            },
            {
                "name": "3G2,5:782",
                "min": [
                    27140.726533,
                    28219.3,
                    2594.3
                ],
                "max": [
                    27358.214425,
                    28230.7,
                    2605.7
                ]
            },
            {
                "name": "3G2,5:783",
                "min": [
                    27084.026533,
                    28276.0,
                    2594.3
                ],
                "max": [
                    27095.426533,
                    28521.525094,
                    2605.7
                ]
            },
            {
                "name": "3G2,5:784",
                "min": [
                    27084.026533,
                    28219.3,
                    2594.331225
                ],
                "max": [
                    27140.726533,
                    28276.0,
                    2605.668775
                ]
            },
            {
                "name": "3G2,5:785",
                "min": [
                    27084.026533,
                    28566.825094,
                    2251.0
                ],
                "max": [
                    27095.426533,
                    28578.225094,
                    2549.0
                ]
            },
            {
                "name": "3G2,5:786",
                "min": [
                    27084.057758,
                    28521.525094,
                    2549.0
                ],
                "max": [
                    27095.395308,
                    28578.225094,
                    2605.7
                ]
            },
            {
                "name": "CHP60-BW:0097",
                "min": [
                    21354.0,
                    26895.562388,
                    2600.0
                ],
                "max": [
                    21514.0,
                    27055.562388,
                    2678.0
                ]
            },
            {
                "name": "CHP60-BW:0098",
                "min": [
                    25174.0,
                    26895.562388,
                    2600.0
                ],
                "max": [
                    25334.0,
                    27055.562388,
                    2678.0
                ]
            },
            {
                "name": "CHP60-BW:0122",
                "min": [
                    22829.0,
                    26894.053422,
                    2600.0
                ],
                "max": [
                    22989.0,
                    27054.053422,
                    2678.0
                ]
            },
            {
                "name": "Part1.sat:8",
                "min": [
                    20895.459066,
                    25497.0,
                    1230.618286
                ],
                "max": [
                    20896.946016,
                    25498.0,
                    1233.676166
                ]
            },
            {
                "name": "Part2.sat:8",
                "min": [
                    20871.663923,
                    25496.0,
                    1221.854224
                ],
                "max": [
                    20873.569037,
                    25498.0,
                    1224.966444
                ]
            },
            {
                "name": "Part3.sat:8",
                "min": [
                    20863.500495,
                    25496.0,
                    1198.287523
                ],
                "max": [
                    20865.293727,
                    25497.0,
                    1201.51372
                ]
            },
            {
                "name": "asp 1 fase:82",
                "min": [
                    27358.214425,
                    28187.5,
                    2562.5
                ],
                "max": [
                    27360.214425,
                    28262.5,
                    2637.5
                ]
            },
            {
                "name": "asp 1 fase:91",
                "min": [
                    21378.5,
                    25480.0,
                    1762.5
                ],
                "max": [
                    21453.5,
                    25482.0,
                    1837.5
                ]
            },
            {
                "name": "brandmelder:0021",
                "min": [
                    22810.4,
                    26875.453422,
                    2543.5
                ],
                "max": [
                    23007.6,
                    27072.653422,
                    2600.0
                ]
            },
            {
                "name": "ledige leiding:0136",
                "min": [
                    21050.65,
                    28461.403422,
                    2359.65
                ],
                "max": [
                    21131.35,
                    28477.403422,
                    2440.35
                ]
            },
            {
                "name": "wcd enkelvoudig:0043",
                "min": [
                    22505.65,
                    25475.4,
                    1880.65
                ],
                "max": [
                    22586.35,
                    25491.4,
                    1961.35
                ]
            },
            {
                "name": "wcd enkelvoudig op aparte groep:0028",
                "min": [
                    21855.675316,
                    25475.4,
                    59.65
                ],
                "max": [
                    21936.375316,
                    25491.4,
                    140.35
                ]
            },
            {
                "name": "wcd inbouw tweevoudig:0056",
                "min": [
                    23971.1,
                    25491.4,
                    259.65
                ],
                "max": [
                    24122.9,
                    25507.4,
                    340.35
                ]
            },
            {
                "name": "wcd inbouw tweevoudig:0062",
                "min": [
                    21820.125316,
                    25475.4,
                    1159.65
                ],
                "max": [
                    21971.925316,
                    25491.4,
                    1240.35
                ]
            },
            {
                "name": "wcd inbouw tweevoudig:0112",
                "min": [
                    20610.1,
                    25468.8,
                    1159.65
                ],
                "max": [
                    20761.9,
                    25484.8,
                    1240.35
                ]
            },
            {
                "name": "wcd inbouw tweevoudig:0160",
                "min": [
                    26866.1,
                    25484.8,
                    259.65
                ],
                "max": [
                    27017.9,
                    25500.8,
                    340.35
                ]
            }
        ],
        "lucht": [],
        "Riolering": [],
        "Sanitair": []
    },
    "adjacent": [
        [
            15
        ],
        [],
        [
            14
        ],
        [],
        [
            46
        ],
        []
    ]
}