{
  "id": 136,
  "min": [
    0,
    0,
    0
  ],
  "max": [
    1,
    1,
    1
  ],
  "objects": {
    "CV_GKW": [],
    "ET": [
      {
        "name": "CHP60-BW:0364",
        "min": [
          0.7928974628448486,
          0.2894110679626465,
          0.9023255705833435
        ],
        "max": [
          0.8123953938484192,
          0.33780792355537415,
          0.9265116453170776
        ]
      },
      {
        "name": "CHP60-BW:0460",
        "min": [
          0.3135480284690857,
          0.38807231187820435,
          0.9023255705833435
        ],
        "max": [
          0.33304595947265625,
          0.436469167470932,
          0.9265116453170776
        ]
      },
      {
        "name": "asp 1 fase:119",
        "min": [
          0.10681156069040298,
          0.4244665503501892,
          0.8286821842193604
        ],
        "max": [
          0.10705528408288956,
          0.4471525549888611,
          0.851938009262085
        ]
      },
      {
        "name": "lasdoos AK2 wand:44",
        "min": [
          0.5670795440673828,
          0.949995756149292,
          0.843410849571228
        ],
        "max": [
          0.5817029476165771,
          0.9636073708534241,
          0.8713178038597107
        ]
      },
      {
        "name": "ledige leiding:0043",
        "min": [
          0.6610833406448364,
          0.03485707566142082,
          0.5797365307807922
        ],
        "max": [
          0.6630331873893738,
          0.05926723778247833,
          0.6047595739364624
        ]
      },
      {
        "name": "schakelaar wissel:0022",
        "min": [
          0.9581647515296936,
          0.16648519039154053,
          0.4091939330101013
        ],
        "max": [
          0.9679990410804749,
          0.17217884957790375,
          0.4342169463634491
        ]
      },
      {
        "name": "standaard:37",
        "min": [
          0.8978796005249023,
          0.043267883360385895,
          0.5922480821609497
        ],
        "max": [
          0.9246892333030701,
          0.07018863409757614,
          0.8077519536018372
        ]
      },
      {
        "name": "wcd enkelvoudig:0220",
        "min": [
          0.9546064138412476,
          0.041850004345178604,
          0.8076435327529907
        ],
        "max": [
          0.9644407033920288,
          0.04668968915939331,
          0.8326665163040161
        ]
      },
      {
        "name": "wcd inbouw tweevoudig:0371",
        "min": [
          0.39030271768569946,
          0.9533532857894897,
          0.17663578689098358
        ],
        "max": [
          0.40880143642425537,
          0.9581929445266724,
          0.20165880024433136
        ]
      },
      {
        "name": "wcd inbouw tweevoudig:0372",
        "min": [
          0.9223129153251648,
          0.041850004345178604,
          0.5919688940048218
        ],
        "max": [
          0.932147204875946,
          0.04668968915939331,
          0.6390388607978821
        ]
      },
      {
        "name": "wcd inbouw tweevoudig:0376",
        "min": [
          0.16989396512508392,
          0.9533532857894897,
          0.17663578689098358
        ],
        "max": [
          0.18839263916015625,
          0.9581929445266724,
          0.20165880024433136
        ]
      }
    ],
    "lucht": [],
    "Riolering": [],
    "Sanitair": []
  },
  "adjacent": [
    [
      156
    ],
    [
      47
    ],
    [
      135
    ],
    [],
    [
      216
    ],
    [
      175
    ]
  ]
}